gd_browser/__init__.py
gd_browser/format.py
gd_browser/http.py
gdbrowser-1.1.1.dist-info/METADATA
gdbrowser-1.1.1.dist-info/WHEEL
gdbrowser-1.1.1.dist-info/top_level.txt
gdbrowser-1.1.1.dist-info/RECORD
