Metadata-Version: 2.4
Name: gdbrowser
Version: 1.1.1
Summary: Simple Python API wrapper for GDBrowser
Author: noxzion
Author-email: negroid2281488ilikrilex@gmail.com
Requires-Python: >=3.7
Requires-Dist: requests
Dynamic: author
Dynamic: author-email
Dynamic: requires-dist
Dynamic: requires-python
Dynamic: summary
